checks/__init__.py
checks/prometheus_rule.py
checks/public_resources.py
checks/rbac.py
checks/registry_quay.py
checks/resources.py
checks/valid_k8s.py
cli/__init__.py
cli/main.py
lib/__init__.py
lib/base.py
lib/result.py
lib/runner.py
lib/units.py
lib/utils.py
manifest_bouncer-0.1.1.dist-info/LICENSE
manifest_bouncer-0.1.1.dist-info/METADATA
manifest_bouncer-0.1.1.dist-info/WHEEL
manifest_bouncer-0.1.1.dist-info/entry_points.txt
manifest_bouncer-0.1.1.dist-info/top_level.txt
manifest_bouncer-0.1.1.dist-info/RECORD
