Metadata-Version: 2.1
Name: manifest-bouncer
Version: 0.1.1
Summary: Run checks on k8s/openshift manifests
Home-page: UNKNOWN
Author: Red Hat App-SRE Team
Author-email: sd-app-sre@redhat.com
License: BSD
Platform: UNKNOWN
Classifier: Development Status :: 2 - Pre-Alpha
Classifier: Programming Language :: Python
Classifier: Programming Language :: Python :: 3
Classifier: Programming Language :: Python :: 3.7
Requires-Python: >=3.7
Requires-Dist: anymarkup (<0.9.0,>=0.8.0)
